ctfd_mcp/__init__.py
ctfd_mcp/__main__.py
ctfd_mcp/config.py
ctfd_mcp/ctfd_client.py
ctfd_mcp/main.py
ctfd_mcp/server.py
ctfd_mcp-0.1.1.dist-info/METADATA
ctfd_mcp-0.1.1.dist-info/WHEEL
ctfd_mcp-0.1.1.dist-info/entry_points.txt
ctfd_mcp-0.1.1.dist-info/licenses/LICENSE
ctfd_mcp-0.1.1.dist-info/RECORD
