Metadata-Version: 2.4
Name: ctfd-mcp
Version: 0.1.1
Summary: MCP server for CTFd that lets regular users browse challenges, manage dynamic instances, and submit flags.
Project-URL: Homepage, https://github.com/umbra2728/ctfd-mcp
Project-URL: Repository, https://github.com/umbra2728/ctfd-mcp
Project-URL: Issues, https://github.com/umbra2728/ctfd-mcp/issues
License:                                  Apache License
License-File: LICENSE
Requires-Python: >=3.13
Requires-Dist: anyio>=4.4
Requires-Dist: httpx>=0.28.1
Requires-Dist: mcp>=1.23.3
Requires-Dist: python-dotenv>=1.2.1
